general_solutions/__init__.py
general_solutions/gss.py
general_solutions-0.0.1.dist-info/METADATA
general_solutions-0.0.1.dist-info/WHEEL
general_solutions-0.0.1.dist-info/top_level.txt
general_solutions-0.0.1.dist-info/RECORD
